fingerprint/__init__.py
fingerprint/fingerprint.py
fingerprint-0.1.4.dist-info/LICENSE
fingerprint-0.1.4.dist-info/METADATA
fingerprint-0.1.4.dist-info/WHEEL
fingerprint-0.1.4.dist-info/top_level.txt
fingerprint-0.1.4.dist-info/RECORD
