Metadata-Version: 2.1
Name: fingerprint
Version: 0.1.4
Summary: Document fingerprint generator
Home-page: http://github.com/kailashbuki/fingerprint
Author: Kailash Budhathoki
Author-email: kailash.buki@gmail.com
License: MIT License
Platform: any
Classifier: Development Status :: 4 - Beta
Classifier: Intended Audience :: Developers
Classifier: License :: OSI Approved :: MIT License
Classifier: Operating System :: OS Independent
Classifier: Programming Language :: Python
Classifier: Topic :: Software Development :: Libraries :: Python Modules
Requires-Python: >=3.0
